BGFS/BFS.py
BGFS/__init__.py
BGFS/utils.py
BGFS-1.1.dist-info/LICENSE
BGFS-1.1.dist-info/METADATA
BGFS-1.1.dist-info/WHEEL
BGFS-1.1.dist-info/top_level.txt
BGFS-1.1.dist-info/RECORD
