Metadata-Version: 2.1
Name: BGFS
Version: 1.1
Summary: A Biobjective Feature Selection neural network for High Dimensions, Low Sample data
Author-email: Tina Issa <tina.issa@univ-evry.fr>
Project-URL: Homepage, https://forge.ibisc.univ-evry.fr/tissa/BFS
Project-URL: Documentation, https://bfss.readthedocs.io/
Project-URL: Repository, https://forge.ibisc.univ-evry.fr/tissa/BFS.git
Classifier: Programming Language :: Python :: 3
Classifier: License :: OSI Approved :: MIT License
Classifier: Operating System :: OS Independent
Requires-Python: >=3.8
License-File: LICENSE
